{
  "data":[
    {
      "id": "1",
      "category": "Device Info",
      "name": "name 1",
      "description": "description 1",
      "deviceResourceType": "DEFAULT VALUE",
      "defaultValue": "aaaaaaa",
      "dataType": "None",
      "format": "number",
      "enumerations": [],
      "rangeMin": 0,
      "ragenMax": 1,
      "unitOfMeasurement": "mm",
      "presicion": 1,
      "accuracy": 1
    },
    {
      "id": "2",
      "category": "Sensors",
      "name": "name 2",
      "description": "description 1",
      "deviceResourceType": "DEFAULT VALUE",
      "defaultValue": "aaaaaaa",
      "dataType": "CDATA",
      "format": "number",
      "enumerations": [],
      "rangeMin": 0,
      "ragenMax": 1,
      "unitOfMeasurement": "mm",
      "presicion": 1,
      "accuracy": 1
    },
    {
      "id": "3",
      "category": "Settings",
      "name": "name 3",
      "description": "description 1",
      "deviceResourceType": "DEFAULT VALUE",
      "defaultValue": "aaaaaaa",
      "dataType": "string",
      "format": "number",
      "enumerations": [],
      "rangeMin": 0,
      "ragenMax": 1,
      "unitOfMeasurement": "mm",
      "presicion": 1,
      "accuracy": 1
    },
    {
      "id": "4",
      "category": "Commands",
      "name": "name 4",
      "description": "description 1",
      "deviceResourceType": "DEFAULT VALUE",
      "defaultValue": "aaaaaaa",
      "dataType": "string",
      "format": "number",
      "enumerations": [],
      "rangeMin": 0,
      "ragenMax": 1,
      "unitOfMeasurement": "mm",
      "presicion": 1,
      "accuracy": 1
    },
    {
      "id": "5",
      "category": "Metadata",
      "name": "name 5",
      "description": "description 1",
      "deviceResourceType": "DEFAULT VALUE",
      "defaultValue": "aaaaaaa",
      "dataType": "string",
      "format": "number",
      "enumerations": [],
      "rangeMin": 0,
      "ragenMax": 1,
      "unitOfMeasurement": "mm",
      "presicion": 1,
      "accuracy": 1
    },
    {
      "id": "6",
      "category": "Metadata",
      "name": "name 6",
      "description": "description 1",
      "deviceResourceType": "DEFAULT VALUE",
      "defaultValue": "aaaaaaa",
      "dataType": "string",
      "format": "number",
      "enumerations": [],
      "rangeMin": 0,
      "ragenMax": 1,
      "unitOfMeasurement": "mm",
      "presicion": 1,
      "accuracy": 1
    },
    {
      "id": "7",
      "category": "Metadata",
      "name": "name 7",
      "description": "description 1",
      "deviceResourceType": "DEFAULT VALUE",
      "defaultValue": "aaaaaaa",
      "dataType": "string",
      "format": "number",
      "enumerations": [],
      "rangeMin": 0,
      "ragenMax": 1,
      "unitOfMeasurement": "mm",
      "presicion": 1,
      "accuracy": 1
    },
    {
      "id": "8",
      "category": "Settings",
      "name": "name 8",
      "description": "description 1",
      "deviceResourceType": "DEFAULT VALUE",
      "defaultValue": "aaaaaaa",
      "dataType": "string",
      "format": "number",
      "enumerations": [],
      "rangeMin": 0,
      "ragenMax": 1,
      "unitOfMeasurement": "mm",
      "presicion": 1,
      "accuracy": 1
    },
    {
      "id": "9",
      "category": "Commands",
      "name": "name 9",
      "description": "description 1",
      "deviceResourceType": "DEFAULT VALUE",
      "defaultValue": "aaaaaaa",
      "dataType": "string",
      "format": "number",
      "enumerations": [],
      "rangeMin": 0,
      "ragenMax": 1,
      "unitOfMeasurement": "mm",
      "presicion": 1,
      "accuracy": 1
    },
    {
      "id": "10",
      "category": "Device Info",
      "name": "name 10",
      "description": "description 1",
      "deviceResourceType": "DEFAULT VALUE",
      "defaultValue": "aaaaaaa",
      "dataType": "string",
      "format": "number",
      "enumerations": [],
      "rangeMin": 0,
      "ragenMax": 1,
      "unitOfMeasurement": "mm",
      "presicion": 1,
      "accuracy": 1
    },
    {
      "id": "11",
      "category": "Metadata",
      "name": "name 11",
      "description": "description",
      "deviceResourceType": "DEFAULT VALUE",
      "defaultValue": "aaaaaaa",
      "dataType": "string",
      "format": "number",
      "enumerations": [],
      "rangeMin": 0,
      "ragenMax": 1,
      "unitOfMeasurement": "mm",
      "presicion": 1,
      "accuracy": 1
    }
  ]
}
